Metadata-Version: 1.0
Name: qy-cli
Version: 2.9
Summary: a cli for qingyun
Home-page: https://github.com/
Author: tj
Author-email: tj@gmail.com
License: UNKNOWN
Keywords: python english translation dictionary terminal
Platform: UNKNOWN
